chorddb
test
