Metadata-Version: 2.1
Name: chorddb
Version: 0.0.5
Summary: A tablature parser / chord database
Home-page: https://github.com/pignacio/chorddb
Author: Ignacio Rossi
Author-email: rossi.ignacio@gmail.com
License: GPLv3
Keywords: music chord tablature
Platform: UNKNOWN
Classifier: Development Status :: 3 - Alpha
Classifier: License :: OSI Approved :: GNU General Public License v3 (GPLv3)
Classifier: Programming Language :: Python :: 3
Classifier: Programming Language :: Python :: 3.6
